pygifconvert_ka/__init__.py
pygifconvert_ka/convert.py
pygifconvt_ka/__init__.py
pygifconvt_ka/convert.py
pygifconvt_ka-1.0.5.dist-info/LICENSE
pygifconvt_ka-1.0.5.dist-info/METADATA
pygifconvt_ka-1.0.5.dist-info/WHEEL
pygifconvt_ka-1.0.5.dist-info/top_level.txt
pygifconvt_ka-1.0.5.dist-info/RECORD
